gitmatch/__init__.py
gitmatch/py.typed
gitmatch-0.3.0.dist-info/METADATA
gitmatch-0.3.0.dist-info/WHEEL
gitmatch-0.3.0.dist-info/licenses/LICENSE
gitmatch-0.3.0.dist-info/RECORD
