Metadata-Version: 2.4
Name: gitmatch
Version: 0.3.0
Summary: Gitignore-style path matching
Project-URL: Source Code, https://github.com/jwodder/gitmatch
Project-URL: Bug Tracker, https://github.com/jwodder/gitmatch/issues
Project-URL: Documentation, https://gitmatch.readthedocs.io
Author-email: John Thorvald Wodder II <gitmatch@varonathe.org>
License-Expression: MIT
License-File: LICENSE
Keywords: fnmatch,git,gitignore,glob,wildmatch
Classifier: Intended Audience :: Developers
Classifier: Programming Language :: Python :: 3
Classifier: Programming Language :: Python :: 3 :: Only
Classifier: Programming Language :: Python :: 3.10
Classifier: Programming Language :: Python :: 3.11
Classifier: Programming Language :: Python :: 3.12
Classifier: Programming Language :: Python :: 3.13
Classifier: Programming Language :: Python :: 3.14
Classifier: Programming Language :: Python :: Implementation :: CPython
Classifier: Programming Language :: Python :: Implementation :: PyPy
Classifier: Topic :: Software Development :: Version Control :: Git
Classifier: Topic :: Text Processing :: Filters
Classifier: Typing :: Typed
Requires-Python: >=3.10
